pygmid/Lookup.py
pygmid/__init__.py
pygmid/__main__.py
pygmid/constants.py
pygmid/numerical.py
pygmid/pygmid.py
pygmid/utility.py
pygmid/version.py
pygmid/sweep/__init__.py
pygmid/sweep/__main__.py
pygmid/sweep/config.py
pygmid/sweep/pysweep.py
pygmid/sweep/simulator.py
pygmid/sweep/sweep.py
pygmid-1.2.12.dist-info/LICENSE
pygmid-1.2.12.dist-info/METADATA
pygmid-1.2.12.dist-info/WHEEL
pygmid-1.2.12.dist-info/top_level.txt
pygmid-1.2.12.dist-info/RECORD
