Metadata-Version: 2.1
Name: pygmid
Version: 1.2.12
Summary: A python 3 implementation of the gm/ID starter kit
Home-page: https://github.com/madrasalach/pygmid
Author: Cian Ó Domhnaill, Tiarnach Ó Riada, Danylo Galach
Author-email: cian.odonnell@tyndall.ie
Project-URL: Bug Tracker, https://github.com/madrasalach/pygmid/issues
Classifier: Programming Language :: Python :: 3
Classifier: Operating System :: OS Independent
Requires-Python: >=3.4
License-File: LICENSE
Requires-Dist: numpy
Requires-Dist: scipy
Requires-Dist: matplotlib
Requires-Dist: psf_utils
Requires-Dist: tqdm
